python_seispy-1.3.10.dist-info/licenses/LICENSE.txt
seispy/__init__.py
seispy/catalog.py
seispy/ccp3d.py
seispy/ccppara.py
seispy/ccpprofile.py
seispy/decon.py
seispy/distaz.py
seispy/eq.py
seispy/geo.py
seispy/get_cpt.py
seispy/harmonics.py
seispy/hk.py
seispy/hkpara.py
seispy/io.py
seispy/mccc.py
seispy/modcreator.py
seispy/para.py
seispy/plotR.py
seispy/plotRT.py
seispy/psrayp.py
seispy/recalrf.py
seispy/rf.py
seispy/rf2depth_makedata.py
seispy/rfani.py
seispy/rfcorrect.py
seispy/scripts.py
seispy/seisfwd.py
seispy/setuplog.py
seispy/signal.py
seispy/slantstack.py
seispy/utils.py
seispy/ccp/rayplib.py
seispy/core/RFStation.py
seispy/core/__init__.py
seispy/core/depmodel.py
seispy/core/pertmod.py
seispy/data/EventCMT.dat
seispy/data/ak135.vel
seispy/data/cmpVsVp.txt
seispy/data/cyan.mat
seispy/data/iasp91.vel
seispy/data/mtna.vel
seispy/data/prem.vel
seispy/data/saveicon.png
seispy/data/seispy.png
seispy/pickdepth/__init__.py
seispy/pickdepth/get_depth.py
seispy/pickdepth/pickdepthui.py
seispy/pickrf/__init__.py
seispy/pickrf/pickfigure.py
seispy/pickrf/pickui.py
seispy/pickrf/rpickfigure.py
seispy/pickseis/__init__.py
seispy/pickseis/sviewerui.py
python_seispy-1.3.10.dist-info/METADATA
python_seispy-1.3.10.dist-info/WHEEL
python_seispy-1.3.10.dist-info/entry_points.txt
python_seispy-1.3.10.dist-info/top_level.txt
python_seispy-1.3.10.dist-info/RECORD
