Metadata-Version: 2.4
Name: python-seispy
Version: 1.3.10
Summary: A Python package for seismic data processing
Author-email: Mijian Xu <gomijianxu@gmail.com>
License: GPLv3
Project-URL: homepage, https://github.com/xumi1993/seispy
Classifier: Programming Language :: Python
Classifier: Programming Language :: Python :: 3.11
Classifier: Programming Language :: Python :: 3.12
Classifier: Programming Language :: Python :: 3.13
License-File: LICENSE.txt
Requires-Dist: numpy<2.0,>=1.19.0
Requires-Dist: scipy>=1.9.1
Requires-Dist: matplotlib>=3.5.0
Requires-Dist: pandas>=1.0.0
Requires-Dist: obspy>=1.2.1
Requires-Dist: pyside6>=6.2.0
Requires-Dist: scikits-bootstrap>=1.0.0
Requires-Dist: numba
Requires-Dist: pyproj
Provides-Extra: dev
Requires-Dist: pytest; extra == "dev"
Requires-Dist: black; extra == "dev"
Requires-Dist: flake8; extra == "dev"
Dynamic: license-file
